functional_list/__init__.py
functional_list/io.py
functional_list/lazy.py
functional_list/list_functional_mapper.py
functional_list/mixins.py
functional_list/ops.py
functional_list/accelerators/__init__.py
functional_list/accelerators/_local_accel.cpython-311-x86_64-linux-gnu.so
functional_list/accelerators/_local_accel.pyx
functional_list/accelerators/_reduce_accel.cpython-311-x86_64-linux-gnu.so
functional_list/accelerators/_reduce_accel.pyx
functional_list/accelerators/local_accel.py
functional_list/accelerators/reduce_accel.py
functional_list/accelerators/sort_accel.py
functional_list/backend/__init__.py
functional_list/backend/_chunking.py
functional_list/backend/_distributed_utils.py
functional_list/backend/async_backend.py
functional_list/backend/base.py
functional_list/backend/dask_backend.py
functional_list/backend/local.py
functional_list/backend/ray_backend.py
functional_list/backend/serial.py
functional_list/utils/__init__.py
functional_list/utils/tools_for_main_class.py
functional_list-0.2.2.dist-info/METADATA
functional_list-0.2.2.dist-info/WHEEL
functional_list-0.2.2.dist-info/top_level.txt
functional_list-0.2.2.dist-info/RECORD
