Metadata-Version: 2.4
Name: functional_list
Version: 0.2.2
Summary: package for map a list
Author-email: Andrianarivo Tantelitiana RAKOTOARIJAONA <tantelitiana22@gmail.com>
Project-URL: Homepage, https://gitlab.com/Tantelitiana22/list-function-python-project
Keywords: functional,list,map,reduce
Classifier: Programming Language :: Python :: 3
Classifier: Operating System :: OS Independent
Requires-Python: >=3.10
Provides-Extra: ray
Requires-Dist: ray>=2.53.0; python_version >= "3.10" and extra == "ray"
Provides-Extra: dask
Requires-Dist: dask>=2025.12.0; python_version >= "3.10" and extra == "dask"
Provides-Extra: io
Requires-Dist: pyarrow>=22.0.0; python_version >= "3.10" and extra == "io"
Provides-Extra: all
Requires-Dist: functional_list[dask,io,ray]; extra == "all"
